djello/__init__.py
djello/static/djello/custom.css
djello/static/djello/assets/calendar/fullcalendar-init.js
djello/static/djello/assets/calendar/fullcalendar.css
djello/static/djello/assets/calendar/fullcalendar.min.js
djello/static/djello/assets/css/animate.css
djello/static/djello/assets/css/bootstrap-grid.css
djello/static/djello/assets/css/bootstrap-grid.css.map
djello/static/djello/assets/css/bootstrap-grid.min.css
djello/static/djello/assets/css/bootstrap-grid.min.css.map
djello/static/djello/assets/css/bootstrap-reboot.css
djello/static/djello/assets/css/bootstrap-reboot.css.map
djello/static/djello/assets/css/bootstrap-reboot.min.css
djello/static/djello/assets/css/bootstrap-reboot.min.css.map
djello/static/djello/assets/css/bootstrap-select.css
djello/static/djello/assets/css/bootstrap.css
djello/static/djello/assets/css/bootstrap.css.map
djello/static/djello/assets/css/bootstrap.min.css
djello/static/djello/assets/css/bootstrap.min.css.map
djello/static/djello/assets/css/cs-skin-elastic.css
djello/static/djello/assets/css/flag-icon.min.css
djello/static/djello/assets/css/font-awesome.min.css
djello/static/djello/assets/css/normalize.css
djello/static/djello/assets/css/pe-icon-7-filled.css
djello/static/djello/assets/css/style.css
djello/static/djello/assets/css/style.css.map
djello/static/djello/assets/css/themify-icons.css
djello/static/djello/assets/css/variables.css
djello/static/djello/assets/css/charts/chartist.min.css
djello/static/djello/assets/css/lib/chosen/chosen-sprite.png
djello/static/djello/assets/css/lib/chosen/chosen-sprite@2x.png
djello/static/djello/assets/css/lib/chosen/chosen.css
djello/static/djello/assets/css/lib/chosen/chosen.min.css
djello/static/djello/assets/css/lib/datatable/buttons.bootstrap.min.css
djello/static/djello/assets/css/lib/datatable/buttons.dataTables.min.css
djello/static/djello/assets/css/lib/datatable/dataTables.bootstrap.min.css
djello/static/djello/assets/css/lib/vector-map/jqvmap.min.css
djello-1.0a0.dist-info/LICENSE.txt
djello-1.0a0.dist-info/METADATA
djello-1.0a0.dist-info/WHEEL
djello-1.0a0.dist-info/top_level.txt
djello-1.0a0.dist-info/RECORD
