Metadata-Version: 2.1
Name: djello
Version: 1.0a0
Summary: A pretty and configurable admin panel to enhance the default Django Admin Panel based on Ela Admin
Home-page: https://github.com/eshandas/djello
Author: Eshan Das
Author-email: eshandasnit@gmail.com
License: UNKNOWN
Download-URL: https://github.com/eshandas/djello/archive/1.0.a.tar.gz
Keywords: django,admin,panel,dashboard
Platform: UNKNOWN
Requires-Dist: Django (>=2.0)
Requires-Dist: django-widget-tweaks (>=1.4.3)
